fabsfit/__init__.py
fabsfit/constants.py
fabsfit/doyleturner.py
fabsfit/miscfcns.py
fabsfit/parametrization.py
fabsfit/cui/__init__.py
fabsfit/cui/download.py
fabsfit/cui/fabsfit_script.py
fabsfit/cui/fit.py
fabsfit/cui/plot.py
fabsfit/data/__init__.py
fabsfit-0.1.dist-info/METADATA
fabsfit-0.1.dist-info/WHEEL
fabsfit-0.1.dist-info/entry_points.txt
fabsfit-0.1.dist-info/licenses/LICENSE
fabsfit-0.1.dist-info/RECORD
